dcl/__init__.py
dcl/_maps.py
dcl/errors.py
dcl/functions.py
dcl/objects.py
dcl-1.0.0.dist-info/LICENSE
dcl-1.0.0.dist-info/METADATA
dcl-1.0.0.dist-info/WHEEL
dcl-1.0.0.dist-info/top_level.txt
dcl-1.0.0.dist-info/RECORD
