Metadata-Version: 2.1
Name: dcl
Version: 1.0.0
Summary: Python library used for diacritic manipulation.
Home-page: https://github.com/Kreusada/python-dcl
Author: Kreusada
Author-email: kreusadaprojects@gmail.com
License: UNKNOWN
Platform: UNKNOWN
Classifier: Programming Language :: Python :: 3
Classifier: License :: OSI Approved :: MIT License
Classifier: Operating System :: OS Independent
License-File: LICENSE
